gbp_notifications-2.0.0.dist-info/METADATA
gbp_notifications-2.0.0.dist-info/WHEEL
gbp_notifications-2.0.0.dist-info/entry_points.txt
gbp_notifications-2.0.0.dist-info/licenses/LICENSE
gbp_notifications/__init__.py
gbp_notifications/django/__init__.py
gbp_notifications/django/gbp_notifications/__init__.py
gbp_notifications/django/gbp_notifications/apps.py
gbp_notifications/exceptions.py
gbp_notifications/methods/__init__.py
gbp_notifications/methods/email.py
gbp_notifications/methods/pushover.py
gbp_notifications/methods/webhook.py
gbp_notifications/py.typed
gbp_notifications/settings.py
gbp_notifications/signals.py
gbp_notifications/tasks.py
gbp_notifications/templates/__init__.py
gbp_notifications/templates/email_postpull.eml
gbp_notifications/templates/email_published.eml
gbp_notifications/types.py
gbp_notifications/utils.py
gbp_notifications-2.0.0.dist-info/RECORD
