Metadata-Version: 2.1
Name: gbp-notifications
Version: 2.0.0
Summary: Get notifications for GBP events
Author-Email: Albert Hopkins <marduk@letterboxes.org>
License: GPL-3+
Classifier: License :: OSI Approved :: GNU General Public License v3 or later (GPLv3+)
Classifier: Operating System :: POSIX :: Linux
Classifier: Programming Language :: Python :: 3
Classifier: Topic :: System :: Software Distribution
Classifier: Topic :: System :: Systems Administration
Project-URL: homepage, https://github.com/enku/gbp-notifications
Project-URL: repository, https://github.com/enku/gbp-notifications
Requires-Python: >=3.12
Requires-Dist: gentoo-build-publisher>=2.4.0rc1
Requires-Dist: Jinja2>=3.1.2
Requires-Dist: orjson>=3.10.15
Requires-Dist: requests>=2.32.3
